completor/__init__.py
completor/completion.py
completor/config_jobs/run_completor
completor/constants.py
completor/create_output.py
completor/exceptions/__init__.py
completor/exceptions/clean_exceptions.py
completor/exceptions/exceptions.py
completor/get_version.py
completor/hook_implementations/__init__.py
completor/hook_implementations/forward_model_steps.py
completor/hook_implementations/run_completor.py
completor/input_validation.py
completor/launch_args_parser.py
completor/logger.py
completor/main.py
completor/parse.py
completor/prepare_outputs.py
completor/read_casefile.py
completor/read_schedule.py
completor/utils.py
completor/visualization.py
completor/visualize_well.py
completor/wells.py
completor-1.4.0.dist-info/LICENSE
completor-1.4.0.dist-info/METADATA
completor-1.4.0.dist-info/WHEEL
completor-1.4.0.dist-info/entry_points.txt
completor-1.4.0.dist-info/RECORD
