Metadata-Version: 2.1
Name: completor
Version: 1.4.0
Summary: Advanced multi-segmented well completion tool.
Home-page: https://github.com/equinor/completor
License: LGPL-3.0-only
Author: Equinor ASA
Author-email: opensource@equinor.com
Requires-Python: >=3.11,<3.14
Classifier: License :: OSI Approved :: GNU Lesser General Public License v3 (LGPLv3)
Classifier: Natural Language :: English
Classifier: Operating System :: OS Independent
Classifier: Programming Language :: Python :: 3
Classifier: Programming Language :: Python :: 3.11
Classifier: Programming Language :: Python :: 3.12
Classifier: Programming Language :: Python :: 3.13
Provides-Extra: ert
Provides-Extra: test
Requires-Dist: ert (>=14,<15) ; extra == "ert"
Requires-Dist: matplotlib (>=3.9,<4.0)
Requires-Dist: numpy (>=2.0,<3.0)
Requires-Dist: pandas (>=2.2,<3.0)
Requires-Dist: pytest (>=8.3,<9.0) ; extra == "test"
Requires-Dist: pytest-env (>=1,<2) ; extra == "test"
Requires-Dist: pytest-xdist (>=3.6,<4.0) ; extra == "test"
Requires-Dist: rstcheck-core (>=1.2,<2.0) ; extra == "test"
Requires-Dist: tqdm (>=4.66,<5.0)
Project-URL: Bug Tracker, https://github.com/equinor/completor/issues
Project-URL: Documentation, https://equinor.github.io/completor
Project-URL: Repository, https://github.com/equinor/completor
